FSM/UART/UART_FSM.v
//---------------------------------------------------------------
// MODULE : UART PROTOCOL
// AUTHOR : TANVI NARIYA
// DESCRIPTION :
//               UART( 2 Process FSM)
//---------------------------------------------------------------


module uart_fsm(input [7:0]data,input clk,input reset,input start,output reg transmit_data);

reg [1:0]state,next_state;
reg [2:0]count;

reg [7:0]D;

parameter IDLE=1'b0,DATA=1'b1;

//STATE REGISTER
always @(posedge clk)
begin
if(reset) begin
state <= IDLE;
D <= 8'b0;
end
else begin
state <= next_state;
if(!start && state == IDLE)
        D <= data;
else if(state == DATA && count != 3'd7)
        D <= D >> 1;
end
end


//COUNTER
always @(posedge clk)
begin
    
if(reset)
count <= 3'b000;
else if(state == DATA)
begin
    if(count == 3'd7)begin
    transmit_data <= D[0];
    count <= 3'b0;
end
else begin
    count <= count + 1;
    transmit_data <= D[0];
end
end
else
count <= 3'b000;
end

//NEXT STATE LOGIC
always @(*)
begin
next_state = IDLE;
case(state)
IDLE :begin
if(start == 0)
next_state = DATA;
else
next_state = IDLE;
end
DATA :begin
if(count == 3'd7)
next_state = IDLE;
else 
    next_state = DATA;
end
default : next_state = IDLE;
endcase
end



endmodule


module tb;
reg clk,start,reset;
reg [7:0]data;
wire Y;

uart_fsm dut(.clk(clk),.data(data),.reset(reset),.start(start),.transmit_data(Y));

initial
begin
clk = 0;
forever #5 clk = ~clk;
end

initial
begin
$dumpfile("uart_fsm.vcd");
$dumpvars(0,tb);

$monitor("TIME = %0t | Clk = %b | Start = %b | Data = %b | TRANSMITTED DATA = %b ",$time,clk,start,data,Y);
start = 0;data = 8'h9C; reset=1;
#5 reset =0;
#100 $finish;

end

endmodule

FSM/UART/uart_fsm.vcd
$date
	Thu Aug 20 17:48:41 2026
$end
$version
	Icarus Verilog
$end
$timescale
	1s
$end
$scope module tb $end
$var wire 1 ! Y $end
$var reg 1 " clk $end
$var reg 8 # data [7:0] $end
$var reg 1 $ reset $end
$var reg 1 % start $end
$scope module dut $end
$var wire 1 " clk $end
$var wire 8 & data [7:0] $end
$var wire 1 $ reset $end
$var wire 1 % start $end
$var parameter 1 ' DATA $end
$var parameter 1 ( IDLE $end
$var reg 8 ) D [7:0] $end
$var reg 3 * count [2:0] $end
$var reg 2 + next_state [1:0] $end
$var reg 2 , state [1:0] $end
$var reg 1 ! transmit_data $end
$upscope $end
$upscope $end
$enddefinitions $end
$comment Show the parameter values. $end
$dumpall
0(
1'
$end
#0
$dumpvars
bx ,
b0 +
bx *
bx )
b10011100 &
0%
1$
b10011100 #
0"
x!
$end
#5
b1 +
b0 )
b0 ,
0!
b0 *
1"
#10
0"
0$
#15
b1 +
b10011100 )
b1 ,
1"
#20
0"
#25
b1 +
b1001110 )
b1 *
1"
#30
0"
#35
b1 +
b100111 )
b10 *
1"
#40
0"
#45
b1 +
b10011 )
b11 *
1!
1"
#50
0"
#55
b1 +
b1001 )
b100 *
1"
#60
0"
#65
b1 +
b100 )
b101 *
1"
#70
0"
#75
b1 +
b10 )
b110 *
0!
1"
#80
0"
#85
b0 +
b1 )
b111 *
1"
#90
0"
#95
b1 +
b0 *
1!
b0 ,
1"
#100
0"
#105
b1 +
b10011100 )
b1 ,
0!
1"
