FSM/vending_machine/vm.v
//---------------------------------------------------------------
// MODULE : VENDING MACHINE
// AUTHOR : TANVI NARIYA
// DESCRIPTION :
//               VENDING MACHINE WHICH DISPENSE WHEN AMOUNT 
//               10$ AND 15$ inserted.
//---------------------------------------------------------------
module vm(input clk,input reset,input coin10,input coin5,output reg dispense);

//STATE DECLARATION
reg [2:0]state,next_state;

/*STATE ENCODING
STATES S0: WHEN NO COIN INSERTED
        S5 : COIN OF 5 IS INSERTED
        S10 : COIN 10 IS INSERTED
*/
parameter S0 = 3'b001,S5 = 3'b010,S10 = 3'b100;

//STATE REGISTER
always @(posedge clk)
begin
if(reset)
state <= S0;
else
state <= next_state;
end

//NEXT STATE LOGIC
always @(*)
begin
next_state = S0;
case(state)
S0 : begin
    if(coin5)
    next_state = S5;
    else if(coin10)
    next_state = S10;
end
S5 :  begin
    if(coin5)
    next_state = S10;
    else if(coin10)
    next_state = S0;
end
S10 : begin
    if(coin5)
    next_state = S0;
    else 
    next_state = S10;
end
default : next_state = S0;
endcase
end

//OUTPUT LOGIC
always @(*)
begin
    if(state == S5 && (coin10 | coin5))
        dispense = 1;
    else if ((state == S10) && coin5)
        dispense = 1;
    else if((state == S0) && coin10)
    dispense = 1;
    else
    dispense = 0;


end

endmodule



//TEST BENCH
`timescale 1ns/1ps
module tb;
reg clk,reset,coin5,coin10;
wire Y;

vm dut(.clk(clk),.reset(reset),.coin5(coin5),.coin10(coin10),.dispense(Y));

always #5 clk = ~clk;

task coins;
input c5,c10;
begin
coin5 = c5;
coin10 = c10;
end
endtask

initial 
begin
$dumpfile("vm_.vcd");
$dumpvars(0,tb);

$monitor("TIME = %0t | clk =%b | coin5 = %b | coin10 = %b | DISPENSE = %b",$time,clk,coin5,coin10,Y);
clk = 0;reset = 1;coin5 = 1;coin10 = 0;
#10 reset = 0;

// ₹5 → total ₹5
#10 coins(1,0);

// ₹5 → total ₹10 → DISPENSE
#10 coins(1,0);

// No coin
#10 coins(0,0);

// ₹10 → total ₹10 → DISPENSE
#10 coins(0,1);

// No coin
#10 coins(0,0);

// ₹5 → total ₹5
#10 coins(1,0);

// ₹10 → total ₹15 → DISPENSE
#10 coins(0,1);

#10 $finish;

end


endmodule

FSM/vending_machine/vm_.vcd
$date
	Wed Aug 26 13:10:12 2026
$end
$version
	Icarus Verilog
$end
$timescale
	1ps
$end
$scope module tb $end
$var wire 1 ! Y $end
$var reg 1 " clk $end
$var reg 1 # coin10 $end
$var reg 1 $ coin5 $end
$var reg 1 % reset $end
$scope module dut $end
$var wire 1 " clk $end
$var wire 1 # coin10 $end
$var wire 1 $ coin5 $end
$var wire 1 % reset $end
$var parameter 3 & S0 $end
$var parameter 3 ' S10 $end
$var parameter 3 ( S5 $end
$var reg 1 ! dispense $end
$var reg 3 ) next_state [2:0] $end
$var reg 3 * state [2:0] $end
$upscope $end
$scope task coins $end
$var reg 1 + c10 $end
$var reg 1 , c5 $end
$upscope $end
$upscope $end
$enddefinitions $end
$comment Show the parameter values. $end
$dumpall
b10 (
b100 '
b1 &
$end
#0
$dumpvars
x,
x+
bx *
b1 )
1%
1$
0#
0"
0!
$end
#5000
b10 )
b1 *
1"
#10000
0"
0%
#15000
1!
b100 )
b10 *
1"
#20000
0"
0+
1,
#25000
b1 )
b100 *
1"
#30000
0"
#35000
0!
b10 )
b1 *
1"
#40000
b1 )
0"
0$
0,
#45000
1"
#50000
1!
b100 )
0"
1#
1+
#55000
0!
b100 )
b100 *
1"
#60000
b100 )
0"
0#
0+
#65000
1"
#70000
1!
b1 )
0"
1$
1,
#75000
0!
b10 )
b1 *
1"
#80000
1!
b100 )
0"
1#
0$
1+
0,
#85000
0!
b100 )
b100 *
1"
