extra/behavioral/register/Shift_left.v
//---------------------------------------------------------------
// MODULE : SHIFT REGISTER
// AUTHOR : TANVI NARIYA
// DESCRIPTION :
//              4 bit shift register (LEFT)
//---------------------------------------------------------------


module S_r(input clk,input new,input reset,output reg [3:0]Q);

always @(posedge clk)
begin
if (reset)
Q <= 4'h0;
else
Q <= {Q[2:0],new};
end


endmodule



module tb;
reg clk,reset,new;
wire [3:0]Q;

S_r dut(.clk(clk),.reset(reset),.new(new),.Q(Q));

initial
begin
    clk = 0;
    forever #5 clk = ~clk;
end

initial
begin
    $dumpfile("left_reg.vcd");
    $dumpvars(0,tb);

$monitor("TIME = %0t | Q = %b | new = %b | clk = %b | reset = %b",$time,Q,new,clk,reset);

reset=1;new=1;
#10 reset=0;
#10 new=1;
#10 new=0;
#10 new=1;
#10 new=1;
#10 new=1;
#10 new=1;
#10 $finish;

end



endmodule

extra/behavioral/register/left_reg.vcd
$date
	Mon Aug 10 20:56:57 2026
$end
$version
	Icarus Verilog
$end
$timescale
	1s
$end
$scope module tb $end
$var wire 4 ! Q [3:0] $end
$var reg 1 " clk $end
$var reg 1 # new $end
$var reg 1 $ reset $end
$scope module dut $end
$var wire 1 " clk $end
$var wire 1 # new $end
$var wire 1 $ reset $end
$var reg 4 % Q [3:0] $end
$upscope $end
$upscope $end
$enddefinitions $end
#0
$dumpvars
bx %
1$
1#
0"
bx !
$end
#5
b0 !
b0 %
1"
#10
0"
0$
#15
b1 !
b1 %
1"
#20
0"
#25
b11 !
b11 %
1"
#30
0"
0#
#35
b110 !
b110 %
1"
#40
0"
1#
#45
b1101 !
b1101 %
1"
#50
0"
#55
b1011 !
b1011 %
1"
#60
0"
#65
b111 !
b111 %
1"
#70
0"
#75
b1111 !
b1111 %
1"
