extra/behavioral/register/reg.v
//---------------------------------------------------------------
// MODULE : REGISTER
// AUTHOR : TANVI NARIYA
// DESCRIPTION :
//               4-bit register
//---------------------------------------------------------------



module register(input [3:0]D,input clk,input reset,input enable,output reg[3:0]Q);

always @(posedge clk)
begin
   if (reset) 
   Q <= 4'b0000;
   else if (enable)
   Q <= D;

end


endmodule



module tb;

reg [3:0]D;
reg clk,reset,enable;
wire [3:0]Q;

register dut(.D(D),.clk(clk),.enable(enable),.reset(reset),.Q(Q));

initial
begin
clk = 0;
forever #5 clk = ~clk;
end

initial
begin
$dumpfile("register.vcd");
$dumpvars(0,tb);

$monitor("TIME = %t | D = %b | R = %b | E  = %b | Q = %b |",$time,D,reset,enable,Q);
reset = 0; enable = 1;D=1'b1;
#10 D=1'b0;
#10 D=1'b1;reset=1'b0;
#10 D=1'b0;reset=1'b1;
#10 D=1'b1;
#10 $finish;


end


endmodule

extra/behavioral/register/register.vcd
$date
	Mon Aug 10 20:07:48 2026
$end
$version
	Icarus Verilog
$end
$timescale
	1s
$end
$scope module tb $end
$var wire 4 ! Q [3:0] $end
$var reg 4 " D [3:0] $end
$var reg 1 # clk $end
$var reg 1 $ enable $end
$var reg 1 % reset $end
$scope module dut $end
$var wire 4 & D [3:0] $end
$var wire 1 # clk $end
$var wire 1 $ enable $end
$var wire 1 % reset $end
$var reg 4 ' Q [3:0] $end
$upscope $end
$upscope $end
$enddefinitions $end
#0
$dumpvars
bx '
b1 &
0%
1$
0#
b1 "
bx !
$end
#5
b1 !
b1 '
1#
#10
0#
b0 "
b0 &
#15
b0 !
b0 '
1#
#20
0#
b1 "
b1 &
#25
b1 !
b1 '
1#
#30
0#
1%
b0 "
b0 &
#35
b0 !
b0 '
1#
#40
0#
b1 "
b1 &
