FSM/sequence detector/sequence_dectector.v
//---------------------------------------------------------------
// MODULE : SEQUENCE DETECTOR
// AUTHOR : TANVI NARIYA
// DESCRIPTION :
//              3-Bit sequence detector(101)
//---------------------------------------------------------------


module s_d(input new,input clk,output reg Y,input reset);

reg [1:0]state,next_state;
parameter S1=2'b00,S2=2'b01,S3=2'b10;

always @(posedge clk)
begin
        if(reset)
   state <= S1;     
   else
   state <= next_state;
end


always @(*)
begin
next_state = S1;

case(state)
S1 : begin
        if(new)
        next_state=S2;
        else
        next_state=S1;
        end
S2 : begin
        if(new)
        next_state=S1;
        else
        next_state=S3;
        end
S3 : begin
        if(new)
        next_state=S2;
        else
        next_state=S1;
end       
default : next_state = S1;
endcase
end


always @(*)
begin
if((state == S3) && (new == 1))
Y = 1'b1;
else
Y = 1'b0;
end

endmodule

module tb;
reg new,clk,reset;
wire Y;

s_d dut(.new(new),.clk(clk),.Y(Y),.reset(reset));

initial
begin
clk = 0;
forever #5 clk = ~clk;
end

initial
begin
$dumpfile("sequence_dect.vcd");
$dumpvars(0,tb);

$monitor("TIME = %0t | CLK = %b | reset = %b |new = 1 | Y = %b",$time,clk,reset,new,Y);
#10 reset=1;
#10 reset=0;new=1;
#10 new=1;
#10 new=1;
#10 new=0;
#10 new=1;
#10 new=1;
#10 new=0;
#10 new=0;
#10 new=1;
#10 new=1;
#10 new=0;
#10 new=1;
#10 new=0;
#10 new=1;
#10 new=0;
#10 new=1;
#10 new=1;
#10 new=1;
#10 new=0;
#10 new=1;
#10 new=1;
#10 $finish;
end


endmodule

FSM/sequence detector/sequence_dect.vcd
$date
	Sat Aug 15 11:37:53 2026
$end
$version
	Icarus Verilog
$end
$timescale
	1s
$end
$scope module tb $end
$var wire 1 ! Y $end
$var reg 1 " clk $end
$var reg 1 # new $end
$var reg 1 $ reset $end
$scope module dut $end
$var wire 1 " clk $end
$var wire 1 # new $end
$var wire 1 $ reset $end
$var reg 1 ! Y $end
$var reg 2 % next_state [1:0] $end
$var reg 2 & state [1:0] $end
$upscope $end
$upscope $end
$enddefinitions $end
#0
$dumpvars
bx &
bx %
x$
x#
0"
x!
$end
#5
1"
#10
0"
1$
#15
0!
b0 %
b0 &
1"
#20
b1 %
0"
1#
0$
#25
b0 %
b1 &
1"
#30
0"
#35
b1 %
b0 &
1"
#40
0"
#45
b0 %
b1 &
1"
#50
b10 %
0"
0#
#55
b0 %
b10 &
1"
#60
b1 %
1!
0"
1#
#65
0!
b0 %
b1 &
1"
#70
0"
#75
b1 %
b0 &
1"
#80
b0 %
0"
0#
#85
1"
#90
0"
#95
1"
#100
b1 %
0"
1#
#105
b0 %
b1 &
1"
#110
0"
#115
b1 %
b0 &
1"
#120
b0 %
0"
0#
#125
1"
#130
b1 %
0"
1#
#135
b0 %
b1 &
1"
#140
b10 %
0"
0#
#145
b0 %
b10 &
1"
#150
b1 %
1!
0"
1#
#155
0!
b0 %
b1 &
1"
#160
b10 %
0"
0#
#165
b0 %
b10 &
1"
#170
b1 %
1!
0"
1#
#175
0!
b0 %
b1 &
1"
#180
0"
#185
b1 %
b0 &
1"
#190
0"
#195
b0 %
b1 &
1"
#200
b10 %
0"
0#
#205
b0 %
b10 &
1"
#210
b1 %
1!
0"
1#
#215
0!
b0 %
b1 &
1"
#220
0"
#225
b1 %
b0 &
1"
