behavioral/COUNTER/counter.v
//---------------------------------------------------------------
// MODULE : COUNTER
// AUTHOR : TANVI NARIYA
// DESCRIPTION :
//               4- bit counter
//---------------------------------------------------------------


module count(input clk,input reset,input up,output reg [3:0]Q);

always @(posedge clk)
begin
if ((reset == 1) || (Q == 4'hF))
Q <= 4'h0;
else if (up)
Q <= Q + 1;
else if ((up == 0) && (Q == 4'h0))
Q <= 4'hF;
else
Q <= Q - 1;
end

endmodule



module tb;
reg clk,up,reset;
wire [3:0]Q;

count dut(.clk(clk),.reset(reset),.up(up),.Q(Q));

initial 
begin
clk = 0;
forever #5 clk = ~clk;
end

initial
begin
$dumpfile("Counter.vcd");
$dumpvars(0,tb);

$monitor("TIME = %0t | CLK = %b |RESET = %b | UP = %b | COUNT = %b ",$time,clk,reset,up,Q);
reset=1;up=1;
#10 reset=0; up=1;
#10 up=1;
#10 up=1;
#10 up=1;
#10 up=0;
#10 up=0;
#10 up=0;
#10 up=0;
#10 $finish;

end



endmodule

behavioral/COUNTER/Counter.vcd
$date
	Wed Aug 12 09:47:29 2026
$end
$version
	Icarus Verilog
$end
$timescale
	1s
$end
$scope module tb $end
$var wire 4 ! Q [3:0] $end
$var reg 1 " clk $end
$var reg 1 # reset $end
$var reg 1 $ up $end
$scope module dut $end
$var wire 1 " clk $end
$var wire 1 # reset $end
$var wire 1 $ up $end
$var reg 4 % Q [3:0] $end
$upscope $end
$upscope $end
$enddefinitions $end
#0
$dumpvars
bx %
1$
1#
0"
bx !
$end
#5
b0 !
b0 %
1"
#10
0"
0#
#15
b1 !
b1 %
1"
#20
0"
#25
b10 !
b10 %
1"
#30
0"
#35
b11 !
b11 %
1"
#40
0"
#45
b100 !
b100 %
1"
#50
0"
0$
#55
b11 !
b11 %
1"
#60
0"
#65
b10 !
b10 %
1"
#70
0"
#75
b1 !
b1 %
1"
#80
0"
#85
b0 !
b0 %
1"
