behavioral/behavioral/alu/alu.v
//---------------------------------------------------------------
// MODULE : ALU
// AUTHOR : TANVI NARIYA
// DESCRIPTION :
//               one bit alu.
//---------------------------------------------------------------


module alu(input A,input B,input [2:0]operator,output reg Y);



always @(*)
begin
case(operator)
3'b000 : Y = A + B;
3'b001 : Y = A - B;
3'b010 : Y = A * B;
3'b011 : Y = A / B;
3'b100 : Y = A % B;
default : $display("INVALID OPERATION");

endcase
end

endmodule


module tb;
reg A,B;
reg [2:0]op;
wire Y;
integer i;

alu dut(.A(A),.B(B),.operator(op),.Y(Y));

initial 
begin
$dumpfile("alu.vcd");
$dumpvars(0,tb);

$monitor("TIME = %t | A = %b | B = %b | op  = %b | Y = %b |",$time,A,B,op,Y);

A=1'b1;B=1'b1; op = 3'b000;

for(i = 0;i <= 6; i = i + 1)
begin 
#10 op = op + 1;
end
#10 $finish;
end
endmodule

behavioral/behavioral/alu/alu.vcd
$date
	Mon Aug 10 09:40:10 2026
$end
$version
	Icarus Verilog
$end
$timescale
	1s
$end
$scope module tb $end
$var wire 1 ! Y $end
$var reg 1 " A $end
$var reg 1 # B $end
$var reg 3 $ op [2:0] $end
$var integer 32 % i [31:0] $end
$scope module dut $end
$var wire 1 " A $end
$var wire 1 # B $end
$var wire 3 & operator [2:0] $end
$var reg 1 ! Y $end
$upscope $end
$upscope $end
$enddefinitions $end
#0
$dumpvars
b0 &
b0 %
b0 $
1#
1"
0!
$end
#10
b1 %
b1 $
b1 &
#20
1!
b10 %
b10 $
b10 &
#30
b11 %
b11 $
b11 &
#40
0!
b100 %
b100 $
b100 &
#50
b101 %
b101 $
b101 &
#60
b110 %
b110 $
b110 &
#70
b111 %
b111 $
b111 &
