behavioral/behavioral/alu/ALU_4bit.v
//---------------------------------------------------------------
// MODULE : ALU
// AUTHOR : TANVI NARIYA
// DESCRIPTION :
//              4-Bit ALU
//---------------------------------------------------------------


module alu(input [3:0]A,input [3:0]B,input [3:0]op,output reg [3:0]Y,output reg carry,);

always @(*)
begin
    carry = 1'b0;
case(op)
4'h0 : $display("ADD :");{carry,Y} = A + B;
4'h1 : $display("SUB :"); {carry,Y} = A - B;
4'h2 : $display("AND :"); Y = A & B;
4'h3 : $display("OR :"); Y = A | B;
4'h4 : $display("XOR :"); Y = A ^ B;
4'h5 : $display("NOT(A) :"); Y = ~A;
4'h6 : $display("NOR :"); Y = ~(A | B);
4'h7 : $display("INCREAMENT(1) A :"); {carry,Y} = A + 1;
4'h8 : $display("DECREAMENT(1) A"); {carry,Y} = A - 1;
4'h9 : $display("NCREAMENT(1) B :"); {carry,Y} = B + 1;
4'hA : $display("DECREAMENT(1) B :"); {carry,Y} = B - 1;
default : $display("INVALID OPERATION :");Y = 4'h0;
endcase
end

endmodule

module tb;

reg [3:0]A,B,op;
wire carry;
wire [3:0]Y;

alu dut(.A(A),.B(B).op(op),.carry(carry),.Y(Y));

initial
begin
$dumpfile("alu_.vcd");
$dumpvars(0,tb);

$monitor("TIME = %0t | A = %b | B = %b |OPERATOR = %b | Y = %b | CARRY = %b |",$time,A,B,op,Y,carry);
integer i;
for(i = 4'h0 ; i < 4'hB ; i = i + 1)
begin
op = i; #10
end
$finish;

end

endmodule

behavioral/behavioral/alu/alu_.vcd
$date
	Sat Aug 15 12:33:55 2026
$end
$version
	Icarus Verilog
$end
$timescale
	1s
$end
$scope module tb $end
$var wire 1 ! carry $end
$var wire 4 " Y [3:0] $end
$var reg 4 # A [3:0] $end
$var reg 4 $ B [3:0] $end
$var reg 4 % op [3:0] $end
$var integer 32 & i [31:0] $end
$scope module dut $end
$var wire 4 ' A [3:0] $end
$var wire 4 ( B [3:0] $end
$var wire 4 ) op [3:0] $end
$var reg 4 * Y [3:0] $end
$var reg 1 ! carry $end
$upscope $end
$upscope $end
$enddefinitions $end
#0
$dumpvars
b0 *
bx )
b100 (
b1001 '
b0 &
bx %
b100 $
b1001 #
b0 "
0!
$end
#10
b1101 "
b1101 *
b1 &
b0 %
b0 )
#20
b101 "
b101 *
b10 &
b1 %
b1 )
#30
b0 "
b0 *
b11 &
b10 %
b10 )
#40
b1101 "
b1101 *
b100 &
b11 %
b11 )
#50
b101 &
b100 %
b100 )
#60
b110 "
b110 *
b110 &
b101 %
b101 )
#70
b10 "
b10 *
b111 &
b110 %
b110 )
#80
b1010 "
b1010 *
b1000 &
b111 %
b111 )
#90
b1000 "
b1000 *
b1001 &
b1000 %
b1000 )
#100
b101 "
b101 *
b1010 &
b1001 %
b1001 )
#110
b1011 &
b1010 %
b1010 )
