behavioral/COUNTER/MOD_6_count.v
//---------------------------------------------------------------
// MODULE : MOD COUNTER
// AUTHOR : TANVI NARIYA
// DESCRIPTION :
//              MOD-6 COUNTER(UP)
//---------------------------------------------------------------

module mod6(input clk,input reset,output reg [2:0]Y);

always @(negedge clk)
begin
if(reset)
Y <= 3'b000;
else if (Y == 3'b101)
Y <= 3'd0;
else
Y <= Y + 1'b1;
end

endmodule

module tb;
reg clk,reset;
wire [2:0]Y;

mod6 dut(.clk(clk),.reset(reset),.Y(Y));

initial
begin
clk = 0;
forever #5 clk = ~clk;
end

initial
begin
$dumpfile("MOD6.vcd");
$dumpvars(0,tb);
$monitor("TIME = %0t | CLK = %b |RESET = %b  | COUNT = %d ",$time,clk,reset,Y);
reset=1;
#10 reset=0;
#100 $finish;
end

endmodule

behavioral/behavioral/counter/MOD6.vcd
$date
	Sat Aug 15 11:54:45 2026
$end
$version
	Icarus Verilog
$end
$timescale
	1s
$end
$scope module tb $end
$var wire 3 ! Y [2:0] $end
$var reg 1 " clk $end
$var reg 1 # reset $end
$scope module dut $end
$var wire 1 " clk $end
$var wire 1 # reset $end
$var reg 3 $ Y [2:0] $end
$upscope $end
$upscope $end
$enddefinitions $end
#0
$dumpvars
b0 $
1#
0"
b0 !
$end
#5
1"
#10
b1 !
b1 $
0"
0#
#15
1"
#20
b10 !
b10 $
0"
#25
1"
#30
b11 !
b11 $
0"
#35
1"
#40
b100 !
b100 $
0"
#45
1"
#50
b101 !
b101 $
0"
#55
1"
#60
b0 !
b0 $
0"
#65
1"
#70
b1 !
b1 $
0"
#75
1"
#80
b10 !
b10 $
0"
#85
1"
#90
b11 !
b11 $
0"
#95
1"
#100
b100 !
b100 $
0"
#105
1"
#110
b101 !
b101 $
0"
