behavioral/D_ff/d_ff.v
module D_ff(input D,input clk,input reset,input enable,output reg Q);

always @(posedge clk)
begin
if (reset == 1)
Q <= 1'b0;
else if (enable == 1)
Q <= D;

end

endmodule


module tb;
reg D;
reg clk,enable,reset;
wire Q;

D_ff dut(.D(D),.clk(clk),.enable(enable),.reset(reset),.Q(Q));

initial
begin
    clk = 0;
    forever #5 clk = ~clk;
end

initial
begin
    $dumpfile("flipflop.vcd");
$dumpvars(0,tb);

$monitor("TIME = %t | D = %b | R = %b | E  = %b | Q = %b |",$time,D,reset,enable,Q);
reset = 0; enable = 1;D=1'b1;
#10 D=1'b0;
#10 D=1'b1;
#10 D=1'b0;
#10 D=1'b1;
#10 $finish;

end

endmodule

behavioral/behavioral/D_ff/flipflop.vcd
$date
	Mon Aug 10 19:54:32 2026
$end
$version
	Icarus Verilog
$end
$timescale
	1s
$end
$scope module tb $end
$var wire 1 ! Q $end
$var reg 1 " D $end
$var reg 1 # clk $end
$var reg 1 $ enable $end
$var reg 1 % reset $end
$scope module dut $end
$var wire 1 " D $end
$var wire 1 # clk $end
$var wire 1 $ enable $end
$var wire 1 % reset $end
$var reg 1 ! Q $end
$upscope $end
$upscope $end
$enddefinitions $end
#0
$dumpvars
0%
1$
0#
1"
x!
$end
#5
1!
1#
#10
0#
0"
#15
0!
1#
#20
0#
1"
#25
1!
1#
#30
0#
0"
#35
0!
1#
#40
0#
1"
#45
1!
1#
