FSM/traffic_light/trafficlight_fsm.v
//---------------------------------------------------------------
// MODULE : TRAFFIC LIGHT CONTROLLER
// AUTHOR : TANVI NARIYA
// DESCRIPTION :
//              Traffic light controller using FSM concept.(2 PROCESS)
//---------------------------------------------------------------

module tl(input clk,input reset,output reg [2:0]SIGNAL);

//STATE DECLARATION AND COUTER
reg [1:0]state,next_state;
reg [3:0]count;

/* STATE ENCODING 
STATE : RED : UNTILL CUNT REACHES 9 THEN MOVE TO YELLOW
        GREEN : UNTILL COUNT REACHES 9 THEN MOVE TO RED
        YELLOW: UNTILL COUNT REACHES 3 THEN MOVE TO GREEN
*/
parameter RED=2'b00,YELLOW=2'b01,GREEN=2'b10;

parameter RED_TIME=5,YELLOW_TIME=3,GREEN_TIME=5;

//STATE REGISTER
always @(posedge clk)
begin
if(reset)
begin
state <= RED;
count <= 3'b0;
end
else 
begin
state <= next_state;

if ((state == RED) && (count == RED_TIME))
count <= 1'b0;
else if ((state == YELLOW) && (count == YELLOW_TIME))
count <= 1'b0;
else if ((state == GREEN) && (count == GREEN_TIME))
count <= 1'b0;
else
count <= count + 1'b1;

end

end

//NEXT STATE LOGIC
always @(*)
begin
next_state = RED;
case(state)
RED : begin
        if(count < RED_TIME)begin
                  next_state = RED;
                  SIGNAL = 3'b100;
                
        end
        else begin
              next_state = YELLOW;
              SIGNAL = 3'b010;
        end

        end
YELLOW : begin
        if(count < YELLOW_TIME)begin
                  next_state = YELLOW;
                  SIGNAL = 3'b010;
        end
        else begin
              next_state = GREEN;
              SIGNAL = 3'b001;
        end
end
GREEN : begin
        if(count < GREEN_TIME)begin
                  next_state = GREEN;
                  SIGNAL = 3'b001;
        end
        else begin
              next_state = RED;
              SIGNAL = 3'b100;
        end
end
default : begin
        next_state = RED;
        SIGNAL = 3'b100;
end
endcase
end


endmodule

//TEST BENCH

`timescale 1ns/1ps
module tb;
reg clk,reset;
wire [2:0]signal;

//driver
tl dut(.clk(clk),.reset(reset),.SIGNAL(signal));

//clock generation
initial
begin
clk = 0;
forever #1 clk = ~clk;
end


initial
begin
$dumpfile("traffic_light.vcd");
$dumpvars(0,tb);

//monitoring
$monitor("TIME = %0t |  |COUNT = %d | STATE = %b | SIGNAL = %b",$time,dut.count,dut.state,signal);

//INITIALIZING CLOCK
reset=1;
#10 reset =0;
#100 $finish;

end

//CHECKING SAFETY PROPERTY
always @(posedge clk)
begin
        if(((|signal) != 1 ))
        begin
                $display("FAIL");
        end
        else
        $display("PASS.");
end


endmodule

FSM/traffic_light/traffic_light.vcd
$date
	Thu Sep 03 10:50:38 2026
$end
$version
	Icarus Verilog
$end
$timescale
	1ps
$end
$scope module tb $end
$var wire 3 ! signal [2:0] $end
$var reg 1 " clk $end
$var reg 1 # reset $end
$scope module dut $end
$var wire 1 " clk $end
$var wire 1 # reset $end
$var parameter 2 $ GREEN $end
$var parameter 32 % GREEN_TIME $end
$var parameter 2 & RED $end
$var parameter 32 ' RED_TIME $end
$var parameter 2 ( YELLOW $end
$var parameter 32 ) YELLOW_TIME $end
$var reg 3 * SIGNAL [2:0] $end
$var reg 4 + count [3:0] $end
$var reg 2 , next_state [1:0] $end
$var reg 2 - state [1:0] $end
$upscope $end
$upscope $end
$enddefinitions $end
$comment Show the parameter values. $end
$dumpall
b11 )
b1 (
b101 '
b0 &
b101 %
b10 $
$end
#0
$dumpvars
bx -
bx ,
bx +
bx *
1#
0"
bx !
$end
#1000
b100 !
b100 *
b0 ,
b0 +
b0 -
1"
#2000
0"
#3000
1"
#4000
0"
#5000
1"
#6000
0"
#7000
1"
#8000
0"
#9000
1"
#10000
0"
0#
#11000
b1 +
1"
#12000
0"
#13000
b10 +
1"
#14000
0"
#15000
b11 +
1"
#16000
0"
#17000
b100 +
1"
#18000
0"
#19000
b10 !
b10 *
b1 ,
b101 +
1"
#20000
0"
#21000
b1 ,
b0 +
b1 -
1"
#22000
0"
#23000
b1 ,
b1 +
1"
#24000
0"
#25000
b1 ,
b10 +
1"
#26000
0"
#27000
b1 !
b1 *
b10 ,
b11 +
1"
#28000
0"
#29000
b10 ,
b0 +
b10 -
1"
#30000
0"
#31000
b10 ,
b1 +
1"
#32000
0"
#33000
b10 ,
b10 +
1"
#34000
0"
#35000
b10 ,
b11 +
1"
#36000
0"
#37000
b10 ,
b100 +
1"
#38000
0"
#39000
b100 !
b100 *
b0 ,
b101 +
1"
#40000
0"
#41000
b0 +
b0 -
1"
#42000
0"
#43000
b1 +
1"
#44000
0"
#45000
b10 +
1"
#46000
0"
#47000
b11 +
1"
#48000
0"
#49000
b100 +
1"
#50000
0"
#51000
b10 !
b10 *
b1 ,
b101 +
1"
#52000
0"
#53000
b1 ,
b0 +
b1 -
1"
#54000
0"
#55000
b1 ,
b1 +
1"
#56000
0"
#57000
b1 ,
b10 +
1"
#58000
0"
#59000
b1 !
b1 *
b10 ,
b11 +
1"
#60000
0"
#61000
b10 ,
b0 +
b10 -
1"
#62000
0"
#63000
b10 ,
b1 +
1"
#64000
0"
#65000
b10 ,
b10 +
1"
#66000
0"
#67000
b10 ,
b11 +
1"
#68000
0"
#69000
b10 ,
b100 +
1"
#70000
0"
#71000
b100 !
b100 *
b0 ,
b101 +
1"
#72000
0"
#73000
b0 +
b0 -
1"
#74000
0"
#75000
b1 +
1"
#76000
0"
#77000
b10 +
1"
#78000
0"
#79000
b11 +
1"
#80000
0"
#81000
b100 +
1"
#82000
0"
#83000
b10 !
b10 *
b1 ,
b101 +
1"
#84000
0"
#85000
b1 ,
b0 +
b1 -
1"
#86000
0"
#87000
b1 ,
b1 +
1"
#88000
0"
#89000
b1 ,
b10 +
1"
#90000
0"
#91000
b1 !
b1 *
b10 ,
b11 +
1"
#92000
0"
#93000
b10 ,
b0 +
b10 -
1"
#94000
0"
#95000
b10 ,
b1 +
1"
#96000
0"
#97000
b10 ,
b10 +
1"
#98000
0"
#99000
b10 ,
b11 +
1"
#100000
0"
#101000
b10 ,
b100 +
1"
#102000
0"
#103000
b100 !
b100 *
b0 ,
b101 +
1"
#104000
0"
#105000
b0 +
b0 -
1"
#106000
0"
#107000
b1 +
1"
#108000
0"
#109000
b10 +
1"
