FSM/sequence_detector/sequence_dectector.v
//---------------------------------------------------------------
// MODULE : SEQUENCE DETECTOR
// AUTHOR : TANVI NARIYA
// DESCRIPTION :
//              3-Bit sequence detector(101) using Mealy fsm
//---------------------------------------------------------------


module s_d(input new,input clk,output reg Y,input reset);

//STATE DECLARATION
reg [1:0]state,next_state;

/*STATE ENCODING
STATES : S1 : IF 1 IS DETECTED MOVE TO S2
         S2 : IF 0 IS DETECTED MOVE TO S3
         S3 : IF 1 IS DETECTED MOVE TO S2(OVERLAPPING IS HAPPENING)
         */
parameter S1=2'b00,S2=2'b01,S3=2'b10;

//STATE REGISTER
always @(posedge clk)
begin
        if(reset)
   state <= S1;     
   else
   state <= next_state;
end

//NEXT STATE LOGIC
always @(*)
begin
next_state = S1;

case(state)
S1 : begin
        if(new)
        next_state=S2;
        else
        next_state=S1;
        end
S2 : begin
        if(new)
        next_state=S1;
        else
        next_state=S3;
        end
S3 : begin
        if(new)
        next_state=S2;
        else
        next_state=S1;
end       
default : next_state = S1;
endcase
end

//OUTPUT LOGIC
always @(*)
begin
if((state == S3) && (new == 1))
Y = 1'b1;
else
Y = 1'b0;
end

endmodule

//TEST BENCH

`timescale 1ns/1ps
module tb;
reg new,clk,reset;
wire Y;

s_d dut(.new(new),.clk(clk),.Y(Y),.reset(reset));

//USING TASK FOR THE INPUTS
task seq;
input i;
begin
        new = i;
        #10;
end
endtask

initial
begin
clk = 0;
forever #5 clk = ~clk;
end

initial
begin
$dumpfile("sequence_dect.vcd");
$dumpvars(0,tb);

$monitor("TIME = %0t | CLK = %b | reset = %b |new = %b Y = %b",$time,clk,reset,new,Y);
#10 reset=1;
#10 reset=0;
seq(1);
seq(0);
seq(1);
seq(1);
seq(1);
seq(1);
seq(0);
seq(0);
seq(1);
seq(0);
seq(1);
seq(1);
seq(0);
seq(1);
#10 $finish;
end


endmodule

FSM/sequence_detector/sequence_dect.vcd
$date
	Sun Aug 30 12:39:06 2026
$end
$version
	Icarus Verilog
$end
$timescale
	1ps
$end
$scope module tb $end
$var wire 1 ! Y $end
$var reg 1 " clk $end
$var reg 1 # new $end
$var reg 1 $ reset $end
$scope module dut $end
$var wire 1 " clk $end
$var wire 1 # new $end
$var wire 1 $ reset $end
$var parameter 2 % S1 $end
$var parameter 2 & S2 $end
$var parameter 2 ' S3 $end
$var reg 1 ! Y $end
$var reg 2 ( next_state [1:0] $end
$var reg 2 ) state [1:0] $end
$upscope $end
$scope task seq $end
$var reg 1 * i $end
$upscope $end
$upscope $end
$enddefinitions $end
$comment Show the parameter values. $end
$dumpall
b10 '
b1 &
b0 %
$end
#0
$dumpvars
x*
bx )
bx (
x$
x#
0"
x!
$end
#5000
1"
#10000
0"
1$
#15000
0!
b0 (
b0 )
1"
#20000
b1 (
0"
1#
1*
0$
#25000
b0 (
b1 )
1"
#30000
b10 (
0"
0#
0*
#35000
b0 (
b10 )
1"
#40000
b1 (
1!
0"
1#
1*
#45000
0!
b0 (
b1 )
1"
#50000
0"
#55000
b1 (
b0 )
1"
#60000
0"
#65000
b0 (
b1 )
1"
#70000
0"
#75000
b1 (
b0 )
1"
#80000
b0 (
0"
0#
0*
#85000
1"
#90000
0"
#95000
1"
#100000
b1 (
0"
1#
1*
#105000
b0 (
b1 )
1"
#110000
b10 (
0"
0#
0*
#115000
b0 (
b10 )
1"
#120000
b1 (
1!
0"
1#
1*
#125000
0!
b0 (
b1 )
1"
#130000
0"
#135000
b1 (
b0 )
1"
#140000
b0 (
0"
0#
0*
#145000
1"
#150000
b1 (
0"
1#
1*
#155000
b0 (
b1 )
1"
#160000
0"
#165000
b1 (
b0 )
1"
