adder_Verification/bit_adder4.v
//---------------------------------------------------------------
// MODULE : 4-BIT ADDER
// AUTHOR : TANVI NARIYA
// DESCRIPTION :
//              A 4-bit adder using self-testing test bench
//---------------------------------------------------------------


// 4 BIT ADDER LOGIC
module adder(input [3:0]A,input [3:0]B,output reg [3:0]Y,output reg C);

always @(*)
begin
    {C,Y} = A + B;
end
endmodule

//SELF CHECKING TEST BENCH
//`timescale 1ns/1ps
module tb;

reg [3:0]A,B;
wire [3:0]Y;
reg [3:0]expected;
reg carry;
wire C;
integer i;
integer error;

// Driver
adder DUT(.A(A),.B(B),.C(C),.Y(Y));

//Wave form
initial
begin
    $dumpfile("adder.vcd");
    $dumpvars(0,tb);
end

initial
begin
    
    //Monitor
    $monitor("TIME = %0t | %b + %b = %b %b",$time,A,B,C,Y);

    error = 0;
    for(i=0;i<20;i=i+1)
    begin
       
    //Generator
    A = $random;
    B = $random;

    {carry,expected} = A + B;

    #1;

    //Scorecard
    if ((Y != expected) || (C != carry))
    begin
        error = error + 1;
        $display("FAIL");
    end
    else
     $display("PASS");

    end

    if(error == 0)
    $display("***************TEST IS SUCCESSFULL****************** (ERROR = %d)",error);
    else
    $display("***************TEST IS UNSUCCESSFULL****************** (ERROR = %d)",error);


end




endmodule

adder_Verification/adder.vcd
$date
	Sat Aug 29 16:57:59 2026
$end
$version
	Icarus Verilog
$end
$timescale
	1s
$end
$scope module tb $end
$var wire 4 ! Y [3:0] $end
$var wire 1 " C $end
$var reg 4 # A [3:0] $end
$var reg 4 $ B [3:0] $end
$var reg 1 % carry $end
$var reg 4 & expected [3:0] $end
$var integer 32 ' error [31:0] $end
$var integer 32 ( i [31:0] $end
$scope module DUT $end
$var wire 4 ) A [3:0] $end
$var wire 4 * B [3:0] $end
$var reg 1 " C $end
$var reg 4 + Y [3:0] $end
$upscope $end
$upscope $end
$enddefinitions $end
$comment Show the parameter values. $end
$dumpall
$end
#0
$dumpvars
b101 +
b1 *
b100 )
b0 (
b0 '
b101 &
0%
b1 $
b100 #
0"
b101 !
$end
#1
b1100 !
b1100 +
b1100 &
b11 $
b11 *
b1001 #
b1001 )
b1 (
#2
1"
b1010 !
b1010 +
1%
b1010 &
b1101 $
b1101 *
b1101 #
b1101 )
b10 (
#3
0"
b111 !
b111 +
0%
b111 &
b10 $
b10 *
b101 #
b101 )
b11 (
#4
b1110 !
b1110 +
b1110 &
b1101 $
b1101 *
b1 #
b1 )
b100 (
#5
1"
b11 !
b11 +
1%
b11 &
b110 #
b110 )
b101 (
#6
b1001 !
b1001 +
b1001 &
b1100 $
b1100 *
b1101 #
b1101 )
b110 (
#7
0"
b1111 !
b1111 +
0%
b1111 &
b110 $
b110 *
b1001 #
b1001 )
b111 (
#8
b1010 $
b1010 *
b101 #
b101 )
b1000 (
#9
b1100 !
b1100 +
b1100 &
b111 $
b111 *
b1001 (
#10
1"
b1 !
b1 +
1%
b1 &
b1111 $
b1111 *
b10 #
b10 )
b1010 (
#11
b0 !
b0 +
b0 &
b1110 $
b1110 *
b1011 (
#12
0"
b1101 !
b1101 +
0%
b1101 &
b101 $
b101 *
b1000 #
b1000 )
b1100 (
#13
1"
b1001 !
b1001 +
1%
b1001 &
b1101 $
b1101 *
b1100 #
b1100 )
b1101 (
#14
b10 !
b10 +
b10 &
b101 $
b101 *
b1101 #
b1101 )
b1110 (
#15
0"
b1101 !
b1101 +
0%
b1101 &
b1010 $
b1010 *
b11 #
b11 )
b1111 (
#16
b0 !
b0 +
b0 &
b0 $
b0 *
b0 #
b0 )
b10000 (
#17
1"
b111 !
b111 +
1%
b111 &
b1101 $
b1101 *
b1010 #
b1010 )
b10001 (
#18
0"
b1001 !
b1001 +
0%
b1001 &
b11 $
b11 *
b110 #
b110 )
b10010 (
#19
1"
b0 !
b0 +
1%
b0 &
b1101 #
b1101 )
b10011 (
#20
b10100 (
